whl_nanoradar_conftool.py
whl_nanoradar_conftool-0.0.1.dist-info/METADATA
whl_nanoradar_conftool-0.0.1.dist-info/WHEEL
whl_nanoradar_conftool-0.0.1.dist-info/entry_points.txt
whl_nanoradar_conftool-0.0.1.dist-info/top_level.txt
whl_nanoradar_conftool-0.0.1.dist-info/RECORD
