Metadata-Version: 2.4
Name: whl-nanoradar-conftool
Version: 0.0.1
Summary: config tool for nanoradar
Author-email: Pride Leong <lykling.lyk@gmail.com>
Project-URL: Homepage, https://github.com/wheelos-tools/whl-nanoradar-conftool/tree/main
Project-URL: Bug Tracker, https://github.com/wheelos-tools/whl-nanoradar-conftool/issues
Requires-Python: >3.8
Requires-Dist: cantools
Requires-Dist: click
Requires-Dist: python-can
